xilnex_api/__init__.py
xilnex_api/xilnex_query.py
xilnex_api-0.0.2.dist-info/LICENSE
xilnex_api-0.0.2.dist-info/METADATA
xilnex_api-0.0.2.dist-info/WHEEL
xilnex_api-0.0.2.dist-info/top_level.txt
xilnex_api-0.0.2.dist-info/RECORD
