Metadata-Version: 2.1
Name: xilnex-api
Version: 0.0.2
Summary: A python package to call for xilnex api
Home-page: https://github.com/andrewngg
Author: Andrewngg
Author-email: andrewngg@qq.com
License: UNKNOWN
Platform: UNKNOWN
Classifier: Programming Language :: Python :: 3
Classifier: License :: OSI Approved :: MIT License
Classifier: Operating System :: OS Independent
Requires-Python: >=3.6
